infoservant/VERSION
infoservant/__init__.py
infoservant/infoservant_impl.py
infoservant-1.0.1.dist-info/LICENSE
infoservant-1.0.1.dist-info/METADATA
infoservant-1.0.1.dist-info/WHEEL
infoservant-1.0.1.dist-info/entry_points.txt
infoservant-1.0.1.dist-info/top_level.txt
infoservant-1.0.1.dist-info/RECORD
